<?xml version="1.0" encoding="ISO-8859-1" ?>

<!DOCTYPE plugin
  PUBLIC "-//GRAFFITI/DTD Plugin Descriptin 1.0//EN"
   "http://vanted.ipk-gatersleben.de/dtd/1.0/plugin.dtd">

<plugin>
	<author>Christian Klukas</author>
	<description>Adds maize, barley and Arabidopsis analysis templates to IAP</description>

	<plugindesc>
	     <name>IAP analysis templates</name>
             <main>de.ipk.ag_ba.plugins.pipelines.PluginIAPanalyisTemplates</main>
             <version>1.0</version>
             <available>http://iap.ipk-gatersleben.de</available>
	</plugindesc>
</plugin>